[{"date":"2022-06-24T08:16:54.207Z","name":"Jone Smith","email":"johnsmithson@gmail.com","message":"Hi, \nHave fun!","_id":"62b572f68f18136fc1d05333"},{"date":"2022-06-24T10:29:52.713Z","name":"Henry Jackson","email":"henryredish@gmail.com","message":"Hi,\n\nCan you help me?","_id":"62b592208f18136fc1d05334"},{"date":"2022-06-24T15:46:36.144Z","name":"Edy Cooper","email":"edyandedy@gmail.com","message":"Hi,\nGreat Website!","_id":"62b5dc5c8f18136fc1d05335"},{"date":"2022-06-24T15:50:59.459Z","name":"Paul Finch","email":"pualdesigner@gmail.com","message":"Hi,\nThis is a regular site.","_id":"62b5dd638f18136fc1d05336"},{"date":"2022-06-24T15:53:48.281Z","name":"John Terry","email":"jonhinway@gmail.com","message":"Hi,\nCan you help me?"},{"date":"2022-07-02T13:25:30.470Z","name":"Nadia Cooper","email":"nadiacooper@gmail.com","message":"Hi, there is any help?","_id":"62c04751efe8027d79ece3e2"},{"date":"2022-07-02T14:11:22.791Z","name":"Frank Board","email":"frankie@gmail.com","message":"Hi, thanks","_id":"62c0520cefe8027d79ece3e3"},{"date":"2022-07-02T15:24:19.577Z","name":"Ali Clay","email":"aliclay@gmail.com","message":"Hi, I'm here","_id":"62c06325efe8027d79ece3e4"},{"date":"2022-07-03T10:36:12.907Z","name":"Adrian Lima","email":"adrianlima@gmail.com","message":"Hi,\n\nA blog is perfect!!","_id":"62c17121e6a2b72b6ef47524"},{"date":"2022-07-03T10:38:58.638Z","name":"test","email":"test@gmai","message":"lkdsjf","_id":"62c171c7e6a2b72b6ef47525"},{"date":"2022-07-03T10:40:57.093Z","name":"Jeremy Adel","email":"lsdkjf@lksdjf","message":"lassadkjf","_id":"62c1723d906e92018d16265a"},{"date":"2022-07-03T10:42:05.524Z","name":"asd","email":"sadf@ed","message":"asdf","_id":"62c17282906e92018d16265b"},{"date":"2022-07-03T10:42:29.455Z","name":"asd","email":"d@s","message":"ss","_id":"62c17299d651a8fdd1ec5b02"},{"date":"2022-07-03T10:47:44.313Z","name":"sd","email":"asd@dsf","message":"sdfsdf","_id":"62c173d535021b8810496d2c"},{"date":"2022-07-03T13:22:09.154Z","name":"Paul Finch","email":"paulfinch@gmail.com","message":"I'm ready.","_id":"62c19805ac3397c23746e98b"},{"date":"2022-07-03T13:23:53.880Z","name":"Yori Nillson","email":"yorinilsson@gmail.com","message":"Yessssss","_id":"62c1986ef098e85497ea1c3a"},{"date":"2022-07-03T13:45:22.063Z","name":"Tina Eddie","email":"tinaeddie@gmail.com","message":"Hi there!","_id":"62c19d7688ff0ad4e82657da"},{"date":"2022-07-03T13:47:31.366Z","name":"Allen Rubben","email":"allenrubben@gmail.com","message":"I'm a soccer player!","_id":"62c19df8a882505d56b263f7"},{"date":"2022-07-03T13:49:32.692Z","name":"Feri Feru","email":"feriferu@gmail.com","message":"Hi","_id":"62c19e71a882505d56b263f8"},{"date":"2022-07-03T13:50:35.516Z","name":"William Sheph","email":"williamsheph@gmail.com","message":"Hi","_id":"62c19eb00df29f16c7df6234"},{"date":"2022-07-03T13:51:56.797Z","name":"Henry Jackson","email":"henrytian@gmail.com","message":"Hi","_id":"62c19efc0df29f16c7df6235"},{"date":"2022-07-03T13:56:29.555Z","name":"David Luis","email":"davidluis@gmail.com","message":"Hi","_id":"62c1a00d0df29f16c7df6236"}]